{
    "img_2.jpg": [
        {
            "x": 445,
            "y": 134,
            "w": 339,
            "h": 306,
            "label": "ka 0"
        },
        {
            "x": 535,
            "y": 786,
            "w": -421,
            "h": -207,
            "label": "kp 0"
        },
        {
            "x": 790,
            "y": 746,
            "w": -129,
            "h": -248,
            "label": "kp 1"
        }
    ],
    "img_3.jpg": [
        {
            "x": 734,
            "y": 368,
            "w": -301,
            "h": -306,
            "label": "ka 0"
        },
        {
            "x": 568,
            "y": 839,
            "w": -271,
            "h": -158,
            "label": "kp 0"
        }
    ],
    "img_25.jpg": [
        {
            "x": 280,
            "y": 45,
            "w": 380,
            "h": 327,
            "label": "ka 0"
        }
    ],
    "img_4.jpg": [
        {
            "x": 310,
            "y": 40,
            "w": 380,
            "h": 310,
            "label": "ka 0"
        },
        {
            "x": 432,
            "y": 670,
            "w": -299,
            "h": -239,
            "label": "kp 0"
        },
        {
            "x": 698,
            "y": 557,
            "w": -106,
            "h": -172,
            "label": "kp 1"
        }
    ],
    "img_5.jpg": [
        {
            "x": 369,
            "y": 154,
            "w": 365,
            "h": 341,
            "label": "ka 0"
        }
    ],
    "img_7.jpg": [
        {
            "x": 19,
            "y": 353,
            "w": 257,
            "h": 266,
            "label": "ka 0"
        },
        {
            "x": 630,
            "y": 211,
            "w": -140,
            "h": 113,
            "label": "ka 1"
        }
    ],
    "img_6.jpg": [
        {
            "x": 245,
            "y": 61,
            "w": 382,
            "h": 364,
            "label": "ka 0"
        }
    ],
    "img_8.jpg": [
        {
            "x": 233,
            "y": 29,
            "w": 412,
            "h": 359,
            "label": "ka 0"
        }
    ],
    "img_9.jpg": [
        {
            "x": 446,
            "y": 115,
            "w": 361,
            "h": 400,
            "label": "ka 0"
        }
    ],
    "img_10.jpg": [
        {
            "x": 135,
            "y": 57,
            "w": 290,
            "h": 285,
            "label": "ka 0"
        }
    ],
    "img_11.jpg": [
        {
            "x": 318,
            "y": 504,
            "w": 155,
            "h": 151,
            "label": "ka 0"
        }
    ],
    "img_12.jpg": [
        {
            "x": 368,
            "y": 56,
            "w": 380,
            "h": 353,
            "label": "ka 0"
        }
    ],
    "img_13.jpg": [
        {
            "x": 268,
            "y": 50,
            "w": 469,
            "h": 451,
            "label": "ka 0"
        }
    ],
    "img_14.jpg": [
        {
            "x": 262,
            "y": 9,
            "w": 410,
            "h": 362,
            "label": "ka 0"
        }
    ],
    "img_15.jpg": [
        {
            "x": 143,
            "y": 113,
            "w": 535,
            "h": 430,
            "label": "ka 0"
        }
    ],
    "img_16.jpg": [
        {
            "x": 376,
            "y": 225,
            "w": 277,
            "h": 318,
            "label": "ka 0"
        },
        {
            "x": 341,
            "y": 34,
            "w": -201,
            "h": 266,
            "label": "ka 1"
        }
    ],
    "img_17.jpg": [
        {
            "x": 187,
            "y": 5,
            "w": 349,
            "h": 269,
            "label": "ka 1"
        }
    ],
    "img_18.jpg": [
        {
            "x": 654,
            "y": 511,
            "w": -398,
            "h": -333,
            "label": "ka 0"
        }
    ],
    "img_19.jpg": [
        {
            "x": 663,
            "y": 396,
            "w": -389,
            "h": -346,
            "label": "ka 0"
        }
    ],
    "img_20.jpg": [
        {
            "x": 223,
            "y": 260,
            "w": 266,
            "h": 283,
            "label": "ka 0"
        }
    ],
    "img_21.jpg": [
        {
            "x": 451,
            "y": 451,
            "w": -303,
            "h": -375,
            "label": "ka 0"
        }
    ],
    "img_22.jpg": [
        {
            "x": 479,
            "y": 371,
            "w": -239,
            "h": -252,
            "label": "ka 0"
        }
    ],
    "img_23.jpg": [
        {
            "x": 489,
            "y": 457,
            "w": -428,
            "h": -367,
            "label": "ka 0"
        }
    ],
    "img_24.jpg": [
        {
            "x": 414,
            "y": 513,
            "w": -409,
            "h": -481,
            "label": "ka 0"
        }
    ],
    "img_1.jpg": [
        {
            "x": 375,
            "y": 188,
            "w": 319,
            "h": 297,
            "label": "ka 0"
        },
        {
            "x": 217,
            "y": 612,
            "w": 268,
            "h": 147,
            "label": "kp 0"
        },
        {
            "x": 620,
            "y": 836,
            "w": 78,
            "h": -108,
            "label": "kp 1"
        }
    ]
}